ae_uptime_ce/__init__.py
ae_uptime_ce/validators.py
ae_uptime_ce/celery/__init__.py
ae_uptime_ce/celery/tasks.py
ae_uptime_ce/lib/__init__.py
ae_uptime_ce/lib/ext_json.py
ae_uptime_ce/lib/resolver.py
ae_uptime_ce/migrations/__init__.py
ae_uptime_ce/migrations/env.py
ae_uptime_ce/migrations/script.py.mako
ae_uptime_ce/migrations/versions/9df5db7a0def_initial_migration.py
ae_uptime_ce/models/__init__.py
ae_uptime_ce/models/uptime_metric.py
ae_uptime_ce/models/services/__init__.py
ae_uptime_ce/models/services/uptime_metric.py
ae_uptime_ce/scripts/__init__.py
ae_uptime_ce/scripts/reindex.py
ae_uptime_ce/scripts/uptime_monitor.py
ae_uptime_ce/static/js/ae_uptime_ce.js
ae_uptime_ce/views/__init__.py
ae_uptime_ce/views/api.py
ae_uptime_ce/views/uptime.py
ae_uptime_ce-2.0.0rc1.dist-info/METADATA
ae_uptime_ce-2.0.0rc1.dist-info/WHEEL
ae_uptime_ce-2.0.0rc1.dist-info/entry_points.txt
ae_uptime_ce-2.0.0rc1.dist-info/top_level.txt
ae_uptime_ce-2.0.0rc1.dist-info/RECORD
