Metadata-Version: 2.1
Name: ae-uptime-ce
Version: 2.0.0rc1
Summary: Appenlight Uptime Monitoring CE
Home-page: http://rhodecode.com
Author: RhodeCode GmbH
Author-email: support@rhodecode.com
License: Apache 2.0
Keywords: appenlight uptime monitoring
Platform: UNKNOWN
Classifier: Development Status :: 5 - Production/Stable
Classifier: Intended Audience :: Developers
Classifier: Topic :: System :: Monitoring
Classifier: Programming Language :: Python :: 3 :: Only
Classifier: Programming Language :: Python :: 3.6
Classifier: License :: OSI Approved :: Apache Software License
Requires-Python: >=3.5
Requires-Dist: gevent (>=1.4.0)
Requires-Dist: requests (>=2.21.0)
Requires-Dist: colander (>=1.7)
